mautrix/__init__.py
mautrix/types.py
mautrix/api/__init__.py
mautrix/api/http.py
mautrix/appservice/__init__.py
mautrix/appservice/appservice.py
mautrix/appservice/api/__init__.py
mautrix/appservice/api/appservice.py
mautrix/appservice/api/intent.py
mautrix/appservice/state_store/__init__.py
mautrix/appservice/state_store/abstract.py
mautrix/appservice/state_store/json.py
mautrix/appservice/state_store/pickle.py
mautrix/bridge/__init__.py
mautrix/bridge/_community.py
mautrix/bridge/bridge.py
mautrix/bridge/config.py
mautrix/bridge/custom_puppet.py
mautrix/bridge/matrix.py
mautrix/bridge/portal.py
mautrix/bridge/puppet.py
mautrix/bridge/user.py
mautrix/bridge/commands/__init__.py
mautrix/bridge/commands/handler.py
mautrix/bridge/commands/meta.py
mautrix/bridge/db/__init__.py
mautrix/bridge/db/mx_room_state.py
mautrix/bridge/db/mx_user_profile.py
mautrix/bridge/db/sqlstatestore.py
mautrix/client/__init__.py
mautrix/client/client.py
mautrix/client/dispatcher.py
mautrix/client/store.py
mautrix/client/api/__init__.py
mautrix/client/api/authentication.py
mautrix/client/api/base.py
mautrix/client/api/client.py
mautrix/client/api/events.py
mautrix/client/api/filtering.py
mautrix/client/api/rooms.py
mautrix/client/api/user_data.py
mautrix/client/api/modules/__init__.py
mautrix/client/api/modules/media_repository.py
mautrix/client/api/modules/misc.py
mautrix/client/api/types/__init__.py
mautrix/client/api/types/filter.py
mautrix/client/api/types/media.py
mautrix/client/api/types/misc.py
mautrix/client/api/types/primitive.py
mautrix/client/api/types/users.py
mautrix/client/api/types/event/__init__.py
mautrix/client/api/types/event/account_data.py
mautrix/client/api/types/event/base.py
mautrix/client/api/types/event/ephemeral.py
mautrix/client/api/types/event/generic.py
mautrix/client/api/types/event/message.py
mautrix/client/api/types/event/reaction.py
mautrix/client/api/types/event/redaction.py
mautrix/client/api/types/event/state.py
mautrix/client/api/types/util/__init__.py
blkmautrix-0.0.18.dist-info/LICENSE
blkmautrix-0.0.18.dist-info/METADATA
blkmautrix-0.0.18.dist-info/WHEEL
blkmautrix-0.0.18.dist-info/top_level.txt
blkmautrix-0.0.18.dist-info/RECORD
