Metadata-Version: 2.1
Name: blkmautrix
Version: 0.0.18
Summary: A Python 3 asyncio Matrix framework.
Home-page: https://github.com/tulir/mautrix-python
Author: Tulir Asokan
Author-email: tulir@maunium.net
License: UNKNOWN
Platform: UNKNOWN
Classifier: Development Status :: 4 - Beta
Classifier: License :: OSI Approved :: MIT License
Classifier: Topic :: Communications :: Chat
Classifier: Framework :: AsyncIO
Classifier: Programming Language :: Python
Classifier: Programming Language :: Python :: 3
Classifier: Programming Language :: Python :: 3.6
Classifier: Programming Language :: Python :: 3.7
Requires-Python: ~=3.6
Requires-Dist: aiohttp (<4,>=3.0.1)
Requires-Dist: attrs (>=18.1.0)
Provides-Extra: detect_mimetype
Requires-Dist: python-magic (<0.5,>=0.4.15) ; extra == 'detect_mimetype'
